{
"type": "FeatureCollection",
"features": [
{ "type": "Feature", "properties": { "obj_type": "22-Pipelines, Communication and Electricity Lines", "name": "Unknown", "info": "2214-Long-distance electricity lines", "damage_gra": "No visible damage", "det_method": "Photo-interpretation", "notation": "Not Applicable", "or_src_id": 994, "dmg_src_id": 997, "cd_value": "Not Applicable" }, "geometry": { "type": "LineString", "coordinates": [ [ 23.847984, 37.992015 ], [ 23.848737, 37.992070 ], [ 23.849503, 37.992196 ], [ 23.850924, 37.992626 ], [ 23.852094, 37.992431 ] ] } }
,
{ "type": "Feature", "properties": { "obj_type": "22-Pipelines, Communication and Electricity Lines", "name": "ΚΥΤ ΠΑΛΛΗΝΗΣ - ΚΥΤ ΑΓΙΟΥ ΣΤΕΦΑΝΟΥ", "info": "2214-Long-distance electricity lines", "damage_gra": "No visible damage", "det_method": "Photo-interpretation", "notation": "Not Applicable", "or_src_id": 994, "dmg_src_id": 997, "cd_value": "Not Applicable" }, "geometry": { "type": "LineString", "coordinates": [ [ 23.854990, 38.101538 ], [ 23.854284, 38.100330 ], [ 23.853053, 38.098227 ], [ 23.852090, 38.096581 ], [ 23.850384, 38.093662 ], [ 23.850503, 38.093258 ], [ 23.850540, 38.093134 ], [ 23.850682, 38.092654 ], [ 23.851053, 38.091397 ], [ 23.851911, 38.088497 ], [ 23.852870, 38.085252 ], [ 23.854141, 38.080951 ], [ 23.855128, 38.077611 ], [ 23.855646, 38.075849 ], [ 23.856934, 38.071551 ], [ 23.860340, 38.069039 ], [ 23.862398, 38.067528 ], [ 23.863778, 38.066512 ], [ 23.864447, 38.063461 ], [ 23.863636, 38.061287 ], [ 23.862660, 38.059621 ], [ 23.862833, 38.053840 ], [ 23.862930, 38.049689 ], [ 23.862585, 38.047684 ], [ 23.862637, 38.045837 ], [ 23.861633, 38.042302 ], [ 23.861830, 38.039608 ], [ 23.862007, 38.037402 ], [ 23.862258, 38.034129 ], [ 23.862480, 38.031202 ], [ 23.862560, 38.030174 ] ] } }
,
{ "type": "Feature", "properties": { "obj_type": "22-Pipelines, Communication and Electricity Lines", "name": "ΚΥΤ ΑΡΓΥΡΟΥΠΟΛΗΣ - KYT ΠΑΛΛΗΝΗΣ", "info": "2214-Long-distance electricity lines", "damage_gra": "No visible damage", "det_method": "Photo-interpretation", "notation": "Not Applicable", "or_src_id": 994, "dmg_src_id": 997, "cd_value": "Not Applicable" }, "geometry": { "type": "LineString", "coordinates": [ [ 23.848045, 37.991877 ], [ 23.849693, 37.992753 ], [ 23.851027, 37.992907 ], [ 23.852196, 37.992774 ] ] } }
,
{ "type": "Feature", "properties": { "obj_type": "22-Pipelines, Communication and Electricity Lines", "name": "Unknown", "info": "2214-Long-distance electricity lines", "damage_gra": "No visible damage", "det_method": "Photo-interpretation", "notation": "Not Applicable", "or_src_id": 994, "dmg_src_id": 997, "cd_value": "Not Applicable" }, "geometry": { "type": "LineString", "coordinates": [ [ 23.862216, 37.994574 ], [ 23.860050, 37.993575 ], [ 23.857310, 37.992315 ], [ 23.853321, 37.992534 ], [ 23.852187, 37.992745 ] ] } }
,
{ "type": "Feature", "properties": { "obj_type": "22-Pipelines, Communication and Electricity Lines", "name": "Unknown", "info": "2214-Long-distance electricity lines", "damage_gra": "Possibly damaged", "det_method": "Photo-interpretation", "notation": "Not Applicable", "or_src_id": 994, "dmg_src_id": 4, "cd_value": "Not Applicable" }, "geometry": { "type": "LineString", "coordinates": [ [ 23.888065, 38.043091 ], [ 23.889903, 38.044057 ], [ 23.892048, 38.045182 ], [ 23.894386, 38.047314 ], [ 23.896844, 38.049598 ], [ 23.898730, 38.051305 ], [ 23.900556, 38.052957 ], [ 23.904699, 38.056706 ], [ 23.907757, 38.059483 ], [ 23.910879, 38.062318 ], [ 23.913573, 38.064490 ] ] } }
,
{ "type": "Feature", "properties": { "obj_type": "22-Pipelines, Communication and Electricity Lines", "name": "ΚΥΤ ΠΑΛΛΗΝΗΣ - ΚΥΤ ΑΓΙΟΥ ΣΤΕΦΑΝΟΥ", "info": "2214-Long-distance electricity lines", "damage_gra": "No visible damage", "det_method": "Photo-interpretation", "notation": "Not Applicable", "or_src_id": 994, "dmg_src_id": 997, "cd_value": "Not Applicable" }, "geometry": { "type": "LineString", "coordinates": [ [ 23.855389, 38.101445 ], [ 23.854862, 38.100548 ], [ 23.853509, 38.098243 ], [ 23.852521, 38.096559 ], [ 23.850792, 38.093615 ], [ 23.851464, 38.091351 ], [ 23.852296, 38.088546 ], [ 23.853231, 38.085398 ], [ 23.854503, 38.081109 ], [ 23.855431, 38.077983 ], [ 23.856011, 38.076027 ], [ 23.857276, 38.071731 ], [ 23.857576, 38.071510 ], [ 23.860399, 38.069431 ], [ 23.862689, 38.067744 ], [ 23.864130, 38.066675 ], [ 23.865039, 38.063871 ], [ 23.864208, 38.061866 ], [ 23.863220, 38.059573 ], [ 23.863225, 38.054114 ], [ 23.863332, 38.049668 ], [ 23.862995, 38.047675 ], [ 23.863053, 38.045801 ], [ 23.862030, 38.042276 ], [ 23.862237, 38.039485 ], [ 23.862426, 38.036927 ], [ 23.862658, 38.034051 ], [ 23.862889, 38.031179 ], [ 23.862972, 38.030077 ] ] } }
,
{ "type": "Feature", "properties": { "obj_type": "22-Pipelines, Communication and Electricity Lines", "name": "Unknown", "info": "2214-Long-distance electricity lines", "damage_gra": "No visible damage", "det_method": "Photo-interpretation", "notation": "Not Applicable", "or_src_id": 994, "dmg_src_id": 997, "cd_value": "Not Applicable" }, "geometry": { "type": "LineString", "coordinates": [ [ 23.847202, 37.993774 ], [ 23.847492, 37.993783 ], [ 23.849432, 37.993838 ], [ 23.850325, 37.993473 ], [ 23.851073, 37.993166 ], [ 23.852248, 37.992947 ] ] } }
,
{ "type": "Feature", "properties": { "obj_type": "22-Pipelines, Communication and Electricity Lines", "name": "Unknown", "info": "2214-Long-distance electricity lines", "damage_gra": "No visible damage", "det_method": "Photo-interpretation", "notation": "Not Applicable", "or_src_id": 994, "dmg_src_id": 997, "cd_value": "Not Applicable" }, "geometry": { "type": "LineString", "coordinates": [ [ 23.850379, 37.993642 ], [ 23.851073, 37.993166 ] ] } }
,
{ "type": "Feature", "properties": { "obj_type": "22-Pipelines, Communication and Electricity Lines", "name": "Unknown", "info": "2214-Long-distance electricity lines", "damage_gra": "No visible damage", "det_method": "Photo-interpretation", "notation": "Not Applicable", "or_src_id": 994, "dmg_src_id": 997, "cd_value": "Not Applicable" }, "geometry": { "type": "LineString", "coordinates": [ [ 23.852761, 37.995085 ], [ 23.852668, 37.994736 ], [ 23.852582, 37.994418 ], [ 23.852552, 37.994304 ], [ 23.852432, 37.993857 ], [ 23.852362, 37.993597 ] ] } }
,
{ "type": "Feature", "properties": { "obj_type": "22-Pipelines, Communication and Electricity Lines", "name": "Unknown", "info": "2214-Long-distance electricity lines", "damage_gra": "No visible damage", "det_method": "Photo-interpretation", "notation": "Not Applicable", "or_src_id": 994, "dmg_src_id": 997, "cd_value": "Not Applicable" }, "geometry": { "type": "LineString", "coordinates": [ [ 23.857441, 37.992684 ], [ 23.853382, 37.992745 ], [ 23.852248, 37.992947 ] ] } }
,
{ "type": "Feature", "properties": { "obj_type": "22-Pipelines, Communication and Electricity Lines", "name": "Unknown", "info": "2214-Long-distance electricity lines", "damage_gra": "No visible damage", "det_method": "Photo-interpretation", "notation": "Not Applicable", "or_src_id": 994, "dmg_src_id": 997, "cd_value": "Not Applicable" }, "geometry": { "type": "LineString", "coordinates": [ [ 23.852028, 37.992211 ], [ 23.852094, 37.992431 ], [ 23.852124, 37.992532 ], [ 23.852187, 37.992745 ], [ 23.852196, 37.992774 ], [ 23.852248, 37.992947 ], [ 23.852356, 37.993308 ] ] } }
,
{ "type": "Feature", "properties": { "obj_type": "22-Pipelines, Communication and Electricity Lines", "name": "Unknown", "info": "2214-Long-distance electricity lines", "damage_gra": "No visible damage", "det_method": "Photo-interpretation", "notation": "Not Applicable", "or_src_id": 994, "dmg_src_id": 997, "cd_value": "Not Applicable" }, "geometry": { "type": "LineString", "coordinates": [ [ 23.852432, 37.993857 ], [ 23.854109, 37.993561 ], [ 23.857563, 37.993020 ], [ 23.861335, 37.994938 ], [ 23.864323, 37.994648 ], [ 23.866910, 37.992663 ], [ 23.869802, 37.990441 ], [ 23.872227, 37.988575 ], [ 23.874681, 37.986703 ], [ 23.876807, 37.985058 ], [ 23.877682, 37.982888 ], [ 23.878780, 37.980368 ], [ 23.879689, 37.978283 ], [ 23.880990, 37.975299 ], [ 23.882255, 37.972399 ] ] } }
,
{ "type": "Feature", "properties": { "obj_type": "22-Pipelines, Communication and Electricity Lines", "name": "Unknown", "info": "2214-Long-distance electricity lines", "damage_gra": "No visible damage", "det_method": "Photo-interpretation", "notation": "Not Applicable", "or_src_id": 994, "dmg_src_id": 997, "cd_value": "Not Applicable" }, "geometry": { "type": "LineString", "coordinates": [ [ 23.881792, 37.972507 ], [ 23.880670, 37.975071 ], [ 23.879480, 37.977799 ], [ 23.878392, 37.980292 ], [ 23.877308, 37.982778 ], [ 23.876350, 37.984970 ], [ 23.874332, 37.986516 ], [ 23.871920, 37.988358 ], [ 23.869502, 37.990203 ], [ 23.867068, 37.992066 ], [ 23.864847, 37.993760 ], [ 23.862237, 37.994267 ], [ 23.860055, 37.993272 ], [ 23.857187, 37.991953 ], [ 23.853260, 37.992330 ], [ 23.852124, 37.992532 ] ] } }
,
{ "type": "Feature", "properties": { "obj_type": "22-Pipelines, Communication and Electricity Lines", "name": "ΚΥΤ ΑΡΓΥΡΟΥΠΟΛΗΣ - KYT ΠΑΛΛΗΝΗΣ", "info": "2214-Long-distance electricity lines", "damage_gra": "No visible damage", "det_method": "Photo-interpretation", "notation": "Not Applicable", "or_src_id": 994, "dmg_src_id": 997, "cd_value": "Not Applicable" }, "geometry": { "type": "LineString", "coordinates": [ [ 23.848038, 37.991894 ], [ 23.849429, 37.993607 ], [ 23.850952, 37.994660 ], [ 23.852582, 37.994418 ] ] } }
,
{ "type": "Feature", "properties": { "obj_type": "22-Pipelines, Communication and Electricity Lines", "name": "Unknown", "info": "2214-Long-distance electricity lines", "damage_gra": "No visible damage", "det_method": "Photo-interpretation", "notation": "Not Applicable", "or_src_id": 994, "dmg_src_id": 997, "cd_value": "Not Applicable" }, "geometry": { "type": "LineString", "coordinates": [ [ 23.916006, 37.980121 ], [ 23.914499, 37.980805 ], [ 23.912256, 37.981883 ], [ 23.910489, 37.982639 ], [ 23.910125, 37.982795 ], [ 23.907694, 37.983290 ], [ 23.906760, 37.983466 ], [ 23.905102, 37.983779 ], [ 23.902961, 37.984183 ], [ 23.900705, 37.984609 ], [ 23.898510, 37.985023 ], [ 23.896289, 37.985443 ], [ 23.891244, 37.986419 ] ] } }
,
{ "type": "Feature", "properties": { "obj_type": "215-Harbours, waterways, dams and other waterworks", "name": "Unknown", "info": "21514-Navigable canals", "damage_gra": "No visible damage", "det_method": "Photo-interpretation", "notation": "Not Applicable", "or_src_id": 994, "dmg_src_id": 997, "cd_value": "Not Applicable" }, "geometry": { "type": "LineString", "coordinates": [ [ 23.851624, 38.016267 ], [ 23.851630, 38.016202 ], [ 23.851644, 38.016134 ], [ 23.851687, 38.016002 ] ] } }
,
{ "type": "Feature", "properties": { "obj_type": "215-Harbours, waterways, dams and other waterworks", "name": "Unknown", "info": "2152-Dams", "damage_gra": "No visible damage", "det_method": "Photo-interpretation", "notation": "Not Applicable", "or_src_id": 994, "dmg_src_id": 4, "cd_value": "Not Applicable" }, "geometry": { "type": "LineString", "coordinates": [ [ 23.885916, 38.012709 ], [ 23.886022, 38.012729 ], [ 23.886174, 38.012756 ] ] } }
,
{ "type": "Feature", "properties": { "obj_type": "215-Harbours, waterways, dams and other waterworks", "name": "Unknown", "info": "2152-Dams", "damage_gra": "No visible damage", "det_method": "Photo-interpretation", "notation": "Not Applicable", "or_src_id": 994, "dmg_src_id": 4, "cd_value": "Not Applicable" }, "geometry": { "type": "LineString", "coordinates": [ [ 23.885246, 38.013753 ], [ 23.885101, 38.013716 ], [ 23.884993, 38.013689 ] ] } }
,
{ "type": "Feature", "properties": { "obj_type": "215-Harbours, waterways, dams and other waterworks", "name": "Unknown", "info": "2152-Dams", "damage_gra": "No visible damage", "det_method": "Photo-interpretation", "notation": "Not Applicable", "or_src_id": 994, "dmg_src_id": 4, "cd_value": "Not Applicable" }, "geometry": { "type": "LineString", "coordinates": [ [ 23.888528, 38.018853 ], [ 23.888683, 38.018773 ], [ 23.888852, 38.018686 ] ] } }
,
{ "type": "Feature", "properties": { "obj_type": "215-Harbours, waterways, dams and other waterworks", "name": "Unknown", "info": "2152-Dams", "damage_gra": "No visible damage", "det_method": "Photo-interpretation", "notation": "Not Applicable", "or_src_id": 994, "dmg_src_id": 4, "cd_value": "Not Applicable" }, "geometry": { "type": "LineString", "coordinates": [ [ 23.880511, 38.027159 ], [ 23.880649, 38.027141 ], [ 23.880826, 38.027119 ] ] } }
,
{ "type": "Feature", "properties": { "obj_type": "215-Harbours, waterways, dams and other waterworks", "name": "Unknown", "info": "2152-Dams", "damage_gra": "No visible damage", "det_method": "Photo-interpretation", "notation": "Not Applicable", "or_src_id": 994, "dmg_src_id": 4, "cd_value": "Not Applicable" }, "geometry": { "type": "LineString", "coordinates": [ [ 23.881618, 38.030408 ], [ 23.881806, 38.030456 ], [ 23.882039, 38.030516 ] ] } }
,
{ "type": "Feature", "properties": { "obj_type": "215-Harbours, waterways, dams and other waterworks", "name": "Unknown", "info": "2152-Dams", "damage_gra": "No visible damage", "det_method": "Photo-interpretation", "notation": "Not Applicable", "or_src_id": 994, "dmg_src_id": 4, "cd_value": "Not Applicable" }, "geometry": { "type": "LineString", "coordinates": [ [ 23.882070, 38.031858 ], [ 23.882326, 38.031775 ], [ 23.882587, 38.031690 ] ] } }
,
{ "type": "Feature", "properties": { "obj_type": "215-Harbours, waterways, dams and other waterworks", "name": "Unknown", "info": "2152-Dams", "damage_gra": "No visible damage", "det_method": "Photo-interpretation", "notation": "Not Applicable", "or_src_id": 994, "dmg_src_id": 4, "cd_value": "Not Applicable" }, "geometry": { "type": "LineString", "coordinates": [ [ 23.869351, 38.032031 ], [ 23.868944, 38.032296 ], [ 23.868785, 38.032400 ] ] } }
,
{ "type": "Feature", "properties": { "obj_type": "215-Harbours, waterways, dams and other waterworks", "name": "Unknown", "info": "2152-Dams", "damage_gra": "No visible damage", "det_method": "Photo-interpretation", "notation": "Not Applicable", "or_src_id": 994, "dmg_src_id": 4, "cd_value": "Not Applicable" }, "geometry": { "type": "LineString", "coordinates": [ [ 23.868047, 38.030438 ], [ 23.868042, 38.030400 ], [ 23.868289, 38.030296 ], [ 23.868476, 38.030217 ] ] } }
,
{ "type": "Feature", "properties": { "obj_type": "215-Harbours, waterways, dams and other waterworks", "name": "Unknown", "info": "2152-Dams", "damage_gra": "No visible damage", "det_method": "Photo-interpretation", "notation": "Not Applicable", "or_src_id": 994, "dmg_src_id": 4, "cd_value": "Not Applicable" }, "geometry": { "type": "LineString", "coordinates": [ [ 23.866647, 38.029330 ], [ 23.866862, 38.029442 ], [ 23.866962, 38.029490 ], [ 23.867139, 38.029466 ] ] } }
,
{ "type": "Feature", "properties": { "obj_type": "215-Harbours, waterways, dams and other waterworks", "name": "Unknown", "info": "2152-Dams", "damage_gra": "No visible damage", "det_method": "Photo-interpretation", "notation": "Not Applicable", "or_src_id": 994, "dmg_src_id": 4, "cd_value": "Not Applicable" }, "geometry": { "type": "LineString", "coordinates": [ [ 23.866760, 38.028183 ], [ 23.866579, 38.028325 ], [ 23.866445, 38.028426 ] ] } }
,
{ "type": "Feature", "properties": { "obj_type": "215-Harbours, waterways, dams and other waterworks", "name": "Unknown", "info": "2152-Dams", "damage_gra": "No visible damage", "det_method": "Photo-interpretation", "notation": "Not Applicable", "or_src_id": 994, "dmg_src_id": 4, "cd_value": "Not Applicable" }, "geometry": { "type": "LineString", "coordinates": [ [ 23.865769, 38.026718 ], [ 23.866052, 38.026671 ], [ 23.866197, 38.026647 ] ] } }
,
{ "type": "Feature", "properties": { "obj_type": "22-Pipelines, Communication and Electricity Lines", "name": "Unknown", "info": "2214-Long-distance electricity lines", "damage_gra": "No visible damage", "det_method": "Photo-interpretation", "notation": "Not Applicable", "or_src_id": 994, "dmg_src_id": 997, "cd_value": "Not Applicable" }, "geometry": { "type": "LineString", "coordinates": [ [ 23.913573, 38.064490 ], [ 23.914981, 38.065626 ], [ 23.917810, 38.067907 ], [ 23.919839, 38.069543 ], [ 23.924017, 38.071407 ], [ 23.926377, 38.072449 ], [ 23.928143, 38.073232 ], [ 23.930981, 38.074491 ], [ 23.932737, 38.075247 ], [ 23.935209, 38.077281 ], [ 23.937824, 38.079433 ], [ 23.942182, 38.080883 ], [ 23.942549, 38.081019 ] ] } }
,
{ "type": "Feature", "properties": { "obj_type": "22-Pipelines, Communication and Electricity Lines", "name": "Unknown", "info": "2214-Long-distance electricity lines", "damage_gra": "Possibly damaged", "det_method": "Photo-interpretation", "notation": "Not Applicable", "or_src_id": 994, "dmg_src_id": 4, "cd_value": "Not Applicable" }, "geometry": { "type": "LineString", "coordinates": [ [ 23.864982, 38.031859 ], [ 23.867448, 38.032952 ], [ 23.870528, 38.034314 ], [ 23.874333, 38.037749 ], [ 23.877528, 38.037963 ] ] } }
,
{ "type": "Feature", "properties": { "obj_type": "22-Pipelines, Communication and Electricity Lines", "name": "Unknown", "info": "2214-Long-distance electricity lines", "damage_gra": "No visible damage", "det_method": "Photo-interpretation", "notation": "Not Applicable", "or_src_id": 994, "dmg_src_id": 997, "cd_value": "Not Applicable" }, "geometry": { "type": "LineString", "coordinates": [ [ 23.887288, 38.042682 ], [ 23.887771, 38.042937 ], [ 23.888065, 38.043091 ] ] } }
,
{ "type": "Feature", "properties": { "obj_type": "22-Pipelines, Communication and Electricity Lines", "name": "Unknown", "info": "2214-Long-distance electricity lines", "damage_gra": "Possibly damaged", "det_method": "Photo-interpretation", "notation": "Not Applicable", "or_src_id": 994, "dmg_src_id": 4, "cd_value": "Not Applicable" }, "geometry": { "type": "LineString", "coordinates": [ [ 23.886547, 38.042292 ], [ 23.887288, 38.042682 ] ] } }
,
{ "type": "Feature", "properties": { "obj_type": "22-Pipelines, Communication and Electricity Lines", "name": "Unknown", "info": "2214-Long-distance electricity lines", "damage_gra": "No visible damage", "det_method": "Photo-interpretation", "notation": "Not Applicable", "or_src_id": 994, "dmg_src_id": 997, "cd_value": "Not Applicable" }, "geometry": { "type": "LineString", "coordinates": [ [ 23.885127, 38.041544 ], [ 23.885403, 38.041689 ], [ 23.886547, 38.042292 ] ] } }
,
{ "type": "Feature", "properties": { "obj_type": "22-Pipelines, Communication and Electricity Lines", "name": "Unknown", "info": "2214-Long-distance electricity lines", "damage_gra": "Possibly damaged", "det_method": "Photo-interpretation", "notation": "Not Applicable", "or_src_id": 994, "dmg_src_id": 4, "cd_value": "Not Applicable" }, "geometry": { "type": "LineString", "coordinates": [ [ 23.883477, 38.040681 ], [ 23.885127, 38.041544 ] ] } }
,
{ "type": "Feature", "properties": { "obj_type": "22-Pipelines, Communication and Electricity Lines", "name": "Unknown", "info": "2214-Long-distance electricity lines", "damage_gra": "No visible damage", "det_method": "Photo-interpretation", "notation": "Not Applicable", "or_src_id": 994, "dmg_src_id": 997, "cd_value": "Not Applicable" }, "geometry": { "type": "LineString", "coordinates": [ [ 23.877528, 38.037963 ], [ 23.878919, 38.038056 ], [ 23.881470, 38.039629 ], [ 23.883477, 38.040681 ] ] } }
,
{ "type": "Feature", "properties": { "obj_type": "22-Pipelines, Communication and Electricity Lines", "name": "Unknown", "info": "2214-Long-distance electricity lines", "damage_gra": "No visible damage", "det_method": "Photo-interpretation", "notation": "Not Applicable", "or_src_id": 994, "dmg_src_id": 997, "cd_value": "Not Applicable" }, "geometry": { "type": "LineString", "coordinates": [ [ 23.863249, 38.030981 ], [ 23.864614, 38.031696 ], [ 23.864982, 38.031859 ] ] } }
,
{ "type": "Feature", "properties": { "obj_type": "22-Pipelines, Communication and Electricity Lines", "name": "ΚΥΤ ΠΑΛΛΗΝΗΣ - ΚΥΤ ΑΓΙΟΥ ΣΤΕΦΑΝΟΥ", "info": "2214-Long-distance electricity lines", "damage_gra": "No visible damage", "det_method": "Photo-interpretation", "notation": "Not Applicable", "or_src_id": 994, "dmg_src_id": 997, "cd_value": "Not Applicable" }, "geometry": { "type": "LineString", "coordinates": [ [ 23.863401, 38.024501 ], [ 23.863545, 38.022576 ], [ 23.863756, 38.019986 ], [ 23.863982, 38.017248 ], [ 23.864161, 38.014864 ], [ 23.864360, 38.012317 ], [ 23.864307, 38.010119 ], [ 23.864247, 38.007626 ], [ 23.864184, 38.005026 ], [ 23.863685, 38.002570 ], [ 23.863085, 37.999776 ], [ 23.862623, 37.997174 ], [ 23.860898, 37.995745 ], [ 23.857923, 37.993962 ], [ 23.854235, 37.994004 ], [ 23.852552, 37.994304 ] ] } }
,
{ "type": "Feature", "properties": { "obj_type": "22-Pipelines, Communication and Electricity Lines", "name": "ΚΥΤ ΠΑΛΛΗΝΗΣ - ΚΥΤ ΑΓΙΟΥ ΣΤΕΦΑΝΟΥ", "info": "2214-Long-distance electricity lines", "damage_gra": "Possibly damaged", "det_method": "Photo-interpretation", "notation": "Not Applicable", "or_src_id": 994, "dmg_src_id": 4, "cd_value": "Not Applicable" }, "geometry": { "type": "LineString", "coordinates": [ [ 23.862972, 38.030077 ], [ 23.863079, 38.028657 ], [ 23.863351, 38.025174 ], [ 23.863401, 38.024501 ] ] } }
,
{ "type": "Feature", "properties": { "obj_type": "22-Pipelines, Communication and Electricity Lines", "name": "ΚΥΤ ΠΑΛΛΗΝΗΣ - ΚΥΤ ΑΓΙΟΥ ΣΤΕΦΑΝΟΥ", "info": "2214-Long-distance electricity lines", "damage_gra": "No visible damage", "det_method": "Photo-interpretation", "notation": "Not Applicable", "or_src_id": 994, "dmg_src_id": 997, "cd_value": "Not Applicable" }, "geometry": { "type": "LineString", "coordinates": [ [ 23.862995, 38.024604 ], [ 23.863131, 38.022889 ], [ 23.863353, 38.020054 ], [ 23.863546, 38.017333 ], [ 23.863780, 38.014706 ], [ 23.863957, 38.012314 ], [ 23.863912, 38.010432 ], [ 23.863851, 38.008089 ], [ 23.863780, 38.005055 ], [ 23.863281, 38.002624 ], [ 23.862673, 37.999845 ], [ 23.862246, 37.997282 ], [ 23.860604, 37.996001 ], [ 23.858000, 37.994368 ], [ 23.854367, 37.994444 ], [ 23.852668, 37.994736 ] ] } }
,
{ "type": "Feature", "properties": { "obj_type": "22-Pipelines, Communication and Electricity Lines", "name": "ΚΥΤ ΠΑΛΛΗΝΗΣ - ΚΥΤ ΑΓΙΟΥ ΣΤΕΦΑΝΟΥ", "info": "2214-Long-distance electricity lines", "damage_gra": "Possibly damaged", "det_method": "Photo-interpretation", "notation": "Not Applicable", "or_src_id": 994, "dmg_src_id": 4, "cd_value": "Not Applicable" }, "geometry": { "type": "LineString", "coordinates": [ [ 23.862560, 38.030174 ], [ 23.862649, 38.029015 ] ] } }
,
{ "type": "Feature", "properties": { "obj_type": "22-Pipelines, Communication and Electricity Lines", "name": "ΚΥΤ ΠΑΛΛΗΝΗΣ - ΚΥΤ ΑΓΙΟΥ ΣΤΕΦΑΝΟΥ", "info": "2214-Long-distance electricity lines", "damage_gra": "No visible damage", "det_method": "Photo-interpretation", "notation": "Not Applicable", "or_src_id": 994, "dmg_src_id": 997, "cd_value": "Not Applicable" }, "geometry": { "type": "LineString", "coordinates": [ [ 23.862649, 38.029015 ], [ 23.862692, 38.028466 ] ] } }
,
{ "type": "Feature", "properties": { "obj_type": "22-Pipelines, Communication and Electricity Lines", "name": "ΚΥΤ ΠΑΛΛΗΝΗΣ - ΚΥΤ ΑΓΙΟΥ ΣΤΕΦΑΝΟΥ", "info": "2214-Long-distance electricity lines", "damage_gra": "Possibly damaged", "det_method": "Photo-interpretation", "notation": "Not Applicable", "or_src_id": 994, "dmg_src_id": 4, "cd_value": "Not Applicable" }, "geometry": { "type": "LineString", "coordinates": [ [ 23.862692, 38.028466 ], [ 23.862703, 38.028330 ], [ 23.862911, 38.025673 ], [ 23.862995, 38.024604 ] ] } }

]
}
