{
"type": "FeatureCollection",
"name": "EMSR500_AOI01_DEL_PRODUCT_observedEventP_r1_v1",
"crs": { "type": "name", "properties": { "name": "urn:ogc:def:crs:OGC:1.3:CRS84" } },
"features": [
{ "type": "Feature", "properties": { "event_type": "8-Wildfire", "obj_desc": "Land fire: Brush, bush, Pasture", "det_method": "Photo-interpretation", "notation": "Active Flames", "dmg_src_id": 2 }, "geometry": { "type": "Point", "coordinates": [ 116.06283759400003, -31.746012101999952 ] } },
{ "type": "Feature", "properties": { "event_type": "8-Wildfire", "obj_desc": "Land fire: Brush, bush, Pasture", "det_method": "Photo-interpretation", "notation": "Active Flames", "dmg_src_id": 2 }, "geometry": { "type": "Point", "coordinates": [ 116.084913139000037, -31.738056813999947 ] } },
{ "type": "Feature", "properties": { "event_type": "8-Wildfire", "obj_desc": "Land fire: Brush, bush, Pasture", "det_method": "Photo-interpretation", "notation": "Active Flames", "dmg_src_id": 2 }, "geometry": { "type": "Point", "coordinates": [ 116.095788242000026, -31.747085631999937 ] } },
{ "type": "Feature", "properties": { "event_type": "8-Wildfire", "obj_desc": "Land fire: Brush, bush, Pasture", "det_method": "Photo-interpretation", "notation": "Active Flames", "dmg_src_id": 2 }, "geometry": { "type": "Point", "coordinates": [ 116.088282145000107, -31.722028473999956 ] } },
{ "type": "Feature", "properties": { "event_type": "8-Wildfire", "obj_desc": "Land fire: Brush, bush, Pasture", "det_method": "Photo-interpretation", "notation": "Active Flames", "dmg_src_id": 2 }, "geometry": { "type": "Point", "coordinates": [ 116.089968081000052, -31.720966374999932 ] } },
{ "type": "Feature", "properties": { "event_type": "8-Wildfire", "obj_desc": "Land fire: Brush, bush, Pasture", "det_method": "Photo-interpretation", "notation": "Active Flames", "dmg_src_id": 2 }, "geometry": { "type": "Point", "coordinates": [ 116.089623700000061, -31.720486517999973 ] } },
{ "type": "Feature", "properties": { "event_type": "8-Wildfire", "obj_desc": "Land fire: Brush, bush, Pasture", "det_method": "Photo-interpretation", "notation": "Active Flames", "dmg_src_id": 2 }, "geometry": { "type": "Point", "coordinates": [ 116.089702840000086, -31.719532286999936 ] } },
{ "type": "Feature", "properties": { "event_type": "8-Wildfire", "obj_desc": "Land fire: Brush, bush, Pasture", "det_method": "Photo-interpretation", "notation": "Active Flames", "dmg_src_id": 2 }, "geometry": { "type": "Point", "coordinates": [ 116.092779631000099, -31.719017146999931 ] } },
{ "type": "Feature", "properties": { "event_type": "8-Wildfire", "obj_desc": "Land fire: Brush, bush, Pasture", "det_method": "Photo-interpretation", "notation": "Active Flames", "dmg_src_id": 2 }, "geometry": { "type": "Point", "coordinates": [ 116.093490485000075, -31.717709357999979 ] } },
{ "type": "Feature", "properties": { "event_type": "8-Wildfire", "obj_desc": "Land fire: Brush, bush, Pasture", "det_method": "Photo-interpretation", "notation": "Active Flames", "dmg_src_id": 2 }, "geometry": { "type": "Point", "coordinates": [ 116.094250238000086, -31.718550204999929 ] } },
{ "type": "Feature", "properties": { "event_type": "8-Wildfire", "obj_desc": "Land fire: Brush, bush, Pasture", "det_method": "Photo-interpretation", "notation": "Active Flames", "dmg_src_id": 2 }, "geometry": { "type": "Point", "coordinates": [ 116.090349761000084, -31.717627310999944 ] } },
{ "type": "Feature", "properties": { "event_type": "8-Wildfire", "obj_desc": "Land fire: Brush, bush, Pasture", "det_method": "Photo-interpretation", "notation": "Active Flames", "dmg_src_id": 2 }, "geometry": { "type": "Point", "coordinates": [ 116.091573717000074, -31.713816849999944 ] } },
{ "type": "Feature", "properties": { "event_type": "8-Wildfire", "obj_desc": "Land fire: Brush, bush, Pasture", "det_method": "Photo-interpretation", "notation": "Active Flames", "dmg_src_id": 2 }, "geometry": { "type": "Point", "coordinates": [ 116.09212165100007, -31.707733914999949 ] } },
{ "type": "Feature", "properties": { "event_type": "8-Wildfire", "obj_desc": "Land fire: Brush, bush, Pasture", "det_method": "Photo-interpretation", "notation": "Active Flames", "dmg_src_id": 2 }, "geometry": { "type": "Point", "coordinates": [ 116.084152220000078, -31.708930092999935 ] } },
{ "type": "Feature", "properties": { "event_type": "8-Wildfire", "obj_desc": "Land fire: Brush, bush, Pasture", "det_method": "Photo-interpretation", "notation": "Active Flames", "dmg_src_id": 2 }, "geometry": { "type": "Point", "coordinates": [ 116.08374574000004, -31.70767400099993 ] } },
{ "type": "Feature", "properties": { "event_type": "8-Wildfire", "obj_desc": "Land fire: Brush, bush, Pasture", "det_method": "Photo-interpretation", "notation": "Active Flames", "dmg_src_id": 2 }, "geometry": { "type": "Point", "coordinates": [ 116.095093205000012, -31.703637466999965 ] } },
{ "type": "Feature", "properties": { "event_type": "8-Wildfire", "obj_desc": "Land fire: Brush, bush, Pasture", "det_method": "Photo-interpretation", "notation": "Active Flames", "dmg_src_id": 2 }, "geometry": { "type": "Point", "coordinates": [ 116.092839395000055, -31.705710075999946 ] } },
{ "type": "Feature", "properties": { "event_type": "8-Wildfire", "obj_desc": "Land fire: Brush, bush, Pasture", "det_method": "Photo-interpretation", "notation": "Active Flames", "dmg_src_id": 2 }, "geometry": { "type": "Point", "coordinates": [ 116.101216271000112, -31.734592354999961 ] } },
{ "type": "Feature", "properties": { "event_type": "8-Wildfire", "obj_desc": "Land fire: Brush, bush, Pasture", "det_method": "Photo-interpretation", "notation": "Active Flames", "dmg_src_id": 2 }, "geometry": { "type": "Point", "coordinates": [ 116.104294080000045, -31.734017274999928 ] } },
{ "type": "Feature", "properties": { "event_type": "8-Wildfire", "obj_desc": "Land fire: Brush, bush, Pasture", "det_method": "Photo-interpretation", "notation": "Active Flames", "dmg_src_id": 2 }, "geometry": { "type": "Point", "coordinates": [ 116.106971250000015, -31.716969053999946 ] } },
{ "type": "Feature", "properties": { "event_type": "8-Wildfire", "obj_desc": "Land fire: Brush, bush, Pasture", "det_method": "Photo-interpretation", "notation": "Active Flames", "dmg_src_id": 2 }, "geometry": { "type": "Point", "coordinates": [ 116.106265170000029, -31.717799554999942 ] } },
{ "type": "Feature", "properties": { "event_type": "8-Wildfire", "obj_desc": "Land fire: Brush, bush, Pasture", "det_method": "Photo-interpretation", "notation": "Active Flames", "dmg_src_id": 2 }, "geometry": { "type": "Point", "coordinates": [ 116.107947971000044, -31.717035566999982 ] } },
{ "type": "Feature", "properties": { "event_type": "8-Wildfire", "obj_desc": "Land fire: Brush, bush, Pasture", "det_method": "Photo-interpretation", "notation": "Active Flames", "dmg_src_id": 2 }, "geometry": { "type": "Point", "coordinates": [ 116.111786200000097, -31.71718171699996 ] } },
{ "type": "Feature", "properties": { "event_type": "8-Wildfire", "obj_desc": "Land fire: Brush, bush, Pasture", "det_method": "Photo-interpretation", "notation": "Active Flames", "dmg_src_id": 2 }, "geometry": { "type": "Point", "coordinates": [ 116.113465540000107, -31.716775680999945 ] } },
{ "type": "Feature", "properties": { "event_type": "8-Wildfire", "obj_desc": "Land fire: Brush, bush, Pasture", "det_method": "Photo-interpretation", "notation": "Active Flames", "dmg_src_id": 2 }, "geometry": { "type": "Point", "coordinates": [ 116.115599957000086, -31.712553578999973 ] } },
{ "type": "Feature", "properties": { "event_type": "8-Wildfire", "obj_desc": "Land fire: Brush, bush, Pasture", "det_method": "Photo-interpretation", "notation": "Active Flames", "dmg_src_id": 2 }, "geometry": { "type": "Point", "coordinates": [ 116.11422260900008, -31.710574741999949 ] } },
{ "type": "Feature", "properties": { "event_type": "8-Wildfire", "obj_desc": "Land fire: Brush, bush, Pasture", "det_method": "Photo-interpretation", "notation": "Active Flames", "dmg_src_id": 2 }, "geometry": { "type": "Point", "coordinates": [ 116.11845152, -31.721047179999971 ] } },
{ "type": "Feature", "properties": { "event_type": "8-Wildfire", "obj_desc": "Land fire: Brush, bush, Pasture", "det_method": "Photo-interpretation", "notation": "Active Flames", "dmg_src_id": 2 }, "geometry": { "type": "Point", "coordinates": [ 116.116884018000064, -31.724378127999955 ] } },
{ "type": "Feature", "properties": { "event_type": "8-Wildfire", "obj_desc": "Land fire: Brush, bush, Pasture", "det_method": "Photo-interpretation", "notation": "Active Flames", "dmg_src_id": 2 }, "geometry": { "type": "Point", "coordinates": [ 116.145735544000104, -31.73012453299998 ] } },
{ "type": "Feature", "properties": { "event_type": "8-Wildfire", "obj_desc": "Land fire: Brush, bush, Pasture", "det_method": "Photo-interpretation", "notation": "Active Flames", "dmg_src_id": 2 }, "geometry": { "type": "Point", "coordinates": [ 116.139190945000109, -31.728111223999974 ] } },
{ "type": "Feature", "properties": { "event_type": "8-Wildfire", "obj_desc": "Land fire: Brush, bush, Pasture", "det_method": "Photo-interpretation", "notation": "Active Flames", "dmg_src_id": 2 }, "geometry": { "type": "Point", "coordinates": [ 116.146039440000095, -31.727441189999979 ] } },
{ "type": "Feature", "properties": { "event_type": "8-Wildfire", "obj_desc": "Land fire: Brush, bush, Pasture", "det_method": "Photo-interpretation", "notation": "Active Flames", "dmg_src_id": 2 }, "geometry": { "type": "Point", "coordinates": [ 116.177143403000059, -31.731464998999968 ] } },
{ "type": "Feature", "properties": { "event_type": "8-Wildfire", "obj_desc": "Land fire: Brush, bush, Pasture", "det_method": "Photo-interpretation", "notation": "Active Flames", "dmg_src_id": 2 }, "geometry": { "type": "Point", "coordinates": [ 116.210660079000036, -31.747729668999966 ] } },
{ "type": "Feature", "properties": { "event_type": "8-Wildfire", "obj_desc": "Land fire: Brush, bush, Pasture", "det_method": "Photo-interpretation", "notation": "Active Flames", "dmg_src_id": 2 }, "geometry": { "type": "Point", "coordinates": [ 116.195741643000019, -31.752768449999962 ] } },
{ "type": "Feature", "properties": { "event_type": "8-Wildfire", "obj_desc": "Land fire: Brush, bush, Pasture", "det_method": "Photo-interpretation", "notation": "Active Flames", "dmg_src_id": 2 }, "geometry": { "type": "Point", "coordinates": [ 116.247174034000068, -31.766211337999948 ] } },
{ "type": "Feature", "properties": { "event_type": "8-Wildfire", "obj_desc": "Land fire: Brush, bush, Pasture", "det_method": "Photo-interpretation", "notation": "Active Flames", "dmg_src_id": 2 }, "geometry": { "type": "Point", "coordinates": [ 116.280053621000093, -31.768728762999956 ] } },
{ "type": "Feature", "properties": { "event_type": "8-Wildfire", "obj_desc": "Land fire: Brush, bush, Pasture", "det_method": "Photo-interpretation", "notation": "Active Flames", "dmg_src_id": 2 }, "geometry": { "type": "Point", "coordinates": [ 116.205721983000103, -31.769898167999941 ] } },
{ "type": "Feature", "properties": { "event_type": "8-Wildfire", "obj_desc": "Land fire: Brush, bush, Pasture", "det_method": "Photo-interpretation", "notation": "Active Flames", "dmg_src_id": 2 }, "geometry": { "type": "Point", "coordinates": [ 116.159170672000073, -31.757783745999973 ] } },
{ "type": "Feature", "properties": { "event_type": "8-Wildfire", "obj_desc": "Land fire: Brush, bush, Pasture", "det_method": "Photo-interpretation", "notation": "Active Flames", "dmg_src_id": 2 }, "geometry": { "type": "Point", "coordinates": [ 116.137737629000071, -31.756864711999981 ] } },
{ "type": "Feature", "properties": { "event_type": "8-Wildfire", "obj_desc": "Land fire: Brush, bush, Pasture", "det_method": "Photo-interpretation", "notation": "Active Flames", "dmg_src_id": 2 }, "geometry": { "type": "Point", "coordinates": [ 116.13922599600005, -31.762066481999966 ] } },
{ "type": "Feature", "properties": { "event_type": "8-Wildfire", "obj_desc": "Land fire: Brush, bush, Pasture", "det_method": "Photo-interpretation", "notation": "Active Flames", "dmg_src_id": 2 }, "geometry": { "type": "Point", "coordinates": [ 116.148761998000055, -31.765651373999958 ] } },
{ "type": "Feature", "properties": { "event_type": "8-Wildfire", "obj_desc": "Land fire: Brush, bush, Pasture", "det_method": "Photo-interpretation", "notation": "Active Flames", "dmg_src_id": 2 }, "geometry": { "type": "Point", "coordinates": [ 116.135446914000113, -31.747838290999937 ] } },
{ "type": "Feature", "properties": { "event_type": "8-Wildfire", "obj_desc": "Land fire: Brush, bush, Pasture", "det_method": "Photo-interpretation", "notation": "Active Flames", "dmg_src_id": 2 }, "geometry": { "type": "Point", "coordinates": [ 116.175662482, -31.741003467999974 ] } },
{ "type": "Feature", "properties": { "event_type": "8-Wildfire", "obj_desc": "Land fire: Brush, bush, Pasture", "det_method": "Photo-interpretation", "notation": "Active Flames", "dmg_src_id": 2 }, "geometry": { "type": "Point", "coordinates": [ 116.122728119000044, -31.733966471999963 ] } },
{ "type": "Feature", "properties": { "event_type": "8-Wildfire", "obj_desc": "Land fire: Brush, bush, Pasture", "det_method": "Photo-interpretation", "notation": "Active Flames", "dmg_src_id": 2 }, "geometry": { "type": "Point", "coordinates": [ 116.120803368000111, -31.72336090899995 ] } },
{ "type": "Feature", "properties": { "event_type": "8-Wildfire", "obj_desc": "Land fire: Brush, bush, Pasture", "det_method": "Photo-interpretation", "notation": "Active Flames", "dmg_src_id": 2 }, "geometry": { "type": "Point", "coordinates": [ 116.118737252000074, -31.720362893999948 ] } },
{ "type": "Feature", "properties": { "event_type": "8-Wildfire", "obj_desc": "Land fire: Brush, bush, Pasture", "det_method": "Photo-interpretation", "notation": "Active Flames", "dmg_src_id": 2 }, "geometry": { "type": "Point", "coordinates": [ 116.118847046000042, -31.719826577999982 ] } },
{ "type": "Feature", "properties": { "event_type": "8-Wildfire", "obj_desc": "Land fire: Brush, bush, Pasture", "det_method": "Photo-interpretation", "notation": "Active Flames", "dmg_src_id": 2 }, "geometry": { "type": "Point", "coordinates": [ 116.141436923000015, -31.719264616999965 ] } },
{ "type": "Feature", "properties": { "event_type": "8-Wildfire", "obj_desc": "Land fire: Brush, bush, Pasture", "det_method": "Photo-interpretation", "notation": "Active Flames", "dmg_src_id": 2 }, "geometry": { "type": "Point", "coordinates": [ 116.162111737000032, -31.72978567499996 ] } },
{ "type": "Feature", "properties": { "event_type": "8-Wildfire", "obj_desc": "Land fire: Brush, bush, Pasture", "det_method": "Photo-interpretation", "notation": "Active Flames", "dmg_src_id": 2 }, "geometry": { "type": "Point", "coordinates": [ 116.16421777000005, -31.728516484999943 ] } },
{ "type": "Feature", "properties": { "event_type": "8-Wildfire", "obj_desc": "Land fire: Brush, bush, Pasture", "det_method": "Photo-interpretation", "notation": "Active Flames", "dmg_src_id": 2 }, "geometry": { "type": "Point", "coordinates": [ 116.164847187000078, -31.728401259999941 ] } },
{ "type": "Feature", "properties": { "event_type": "8-Wildfire", "obj_desc": "Land fire: Brush, bush, Pasture", "det_method": "Photo-interpretation", "notation": "Active Flames", "dmg_src_id": 2 }, "geometry": { "type": "Point", "coordinates": [ 116.23748545400008, -31.767973806999976 ] } },
{ "type": "Feature", "properties": { "event_type": "8-Wildfire", "obj_desc": "Land fire: Brush, bush, Pasture", "det_method": "Photo-interpretation", "notation": "Active Flames", "dmg_src_id": 2 }, "geometry": { "type": "Point", "coordinates": [ 116.100131175000115, -31.744359854999971 ] } },
{ "type": "Feature", "properties": { "event_type": "8-Wildfire", "obj_desc": "Land fire: Brush, bush, Pasture", "det_method": "Photo-interpretation", "notation": "Active Flames", "dmg_src_id": 2 }, "geometry": { "type": "Point", "coordinates": [ 116.08797180900001, -31.74524013599995 ] } },
{ "type": "Feature", "properties": { "event_type": "8-Wildfire", "obj_desc": "Land fire: Brush, bush, Pasture", "det_method": "Photo-interpretation", "notation": "Active Flames", "dmg_src_id": 2 }, "geometry": { "type": "Point", "coordinates": [ 116.094445323000059, -31.712930602999961 ] } },
{ "type": "Feature", "properties": { "event_type": "8-Wildfire", "obj_desc": "Land fire: Brush, bush, Pasture", "det_method": "Photo-interpretation", "notation": "Active Flames", "dmg_src_id": 2 }, "geometry": { "type": "Point", "coordinates": [ 116.092711379000093, -31.710340315999929 ] } },
{ "type": "Feature", "properties": { "event_type": "8-Wildfire", "obj_desc": "Land fire: Brush, bush, Pasture", "det_method": "Photo-interpretation", "notation": "Active Flames", "dmg_src_id": 2 }, "geometry": { "type": "Point", "coordinates": [ 116.093855144000031, -31.713320264999936 ] } },
{ "type": "Feature", "properties": { "event_type": "8-Wildfire", "obj_desc": "Land fire: Brush, bush, Pasture", "det_method": "Photo-interpretation", "notation": "Active Flames", "dmg_src_id": 2 }, "geometry": { "type": "Point", "coordinates": [ 116.092425568000067, -31.713882975999979 ] } },
{ "type": "Feature", "properties": { "event_type": "8-Wildfire", "obj_desc": "Land fire: Brush, bush, Pasture", "det_method": "Photo-interpretation", "notation": "Active Flames", "dmg_src_id": 2 }, "geometry": { "type": "Point", "coordinates": [ 116.12562902500008, -31.719593197999984 ] } },
{ "type": "Feature", "properties": { "event_type": "8-Wildfire", "obj_desc": "Land fire: Brush, bush, Pasture", "det_method": "Photo-interpretation", "notation": "Active Flames", "dmg_src_id": 2 }, "geometry": { "type": "Point", "coordinates": [ 116.112490751000109, -31.71366618299993 ] } },
{ "type": "Feature", "properties": { "event_type": "8-Wildfire", "obj_desc": "Land fire: Brush, bush, Pasture", "det_method": "Photo-interpretation", "notation": "Active Flames", "dmg_src_id": 2 }, "geometry": { "type": "Point", "coordinates": [ 116.134085841000115, -31.720086549999962 ] } },
{ "type": "Feature", "properties": { "event_type": "8-Wildfire", "obj_desc": "Land fire: Brush, bush, Pasture", "det_method": "Photo-interpretation", "notation": "Active Flames", "dmg_src_id": 2 }, "geometry": { "type": "Point", "coordinates": [ 116.139933098000029, -31.721940261999976 ] } },
{ "type": "Feature", "properties": { "event_type": "8-Wildfire", "obj_desc": "Land fire: Brush, bush, Pasture", "det_method": "Photo-interpretation", "notation": "Active Flames", "dmg_src_id": 2 }, "geometry": { "type": "Point", "coordinates": [ 116.133119103000013, -31.721941845999936 ] } },
{ "type": "Feature", "properties": { "event_type": "8-Wildfire", "obj_desc": "Land fire: Brush, bush, Pasture", "det_method": "Photo-interpretation", "notation": "Active Flames", "dmg_src_id": 2 }, "geometry": { "type": "Point", "coordinates": [ 116.211717473000022, -31.766468774999964 ] } },
{ "type": "Feature", "properties": { "event_type": "8-Wildfire", "obj_desc": "Land fire: Brush, bush, Pasture", "det_method": "Photo-interpretation", "notation": "Active Flames", "dmg_src_id": 2 }, "geometry": { "type": "Point", "coordinates": [ 116.150880071000074, -31.752567340999974 ] } },
{ "type": "Feature", "properties": { "event_type": "8-Wildfire", "obj_desc": "Land fire: Brush, bush, Pasture", "det_method": "Photo-interpretation", "notation": "Active Flames", "dmg_src_id": 2 }, "geometry": { "type": "Point", "coordinates": [ 116.14933760100007, -31.756280771999968 ] } },
{ "type": "Feature", "properties": { "event_type": "8-Wildfire", "obj_desc": "Land fire: Brush, bush, Pasture", "det_method": "Photo-interpretation", "notation": "Active Flames", "dmg_src_id": 2 }, "geometry": { "type": "Point", "coordinates": [ 116.145216855000058, -31.75477325199995 ] } },
{ "type": "Feature", "properties": { "event_type": "8-Wildfire", "obj_desc": "Land fire: Brush, bush, Pasture", "det_method": "Photo-interpretation", "notation": "Active Flames", "dmg_src_id": 2 }, "geometry": { "type": "Point", "coordinates": [ 116.096227442000099, -31.753719054999976 ] } },
{ "type": "Feature", "properties": { "event_type": "8-Wildfire", "obj_desc": "Land fire: Brush, bush, Pasture", "det_method": "Photo-interpretation", "notation": "Active Flames", "dmg_src_id": 2 }, "geometry": { "type": "Point", "coordinates": [ 116.155692949000013, -31.759688719999929 ] } },
{ "type": "Feature", "properties": { "event_type": "8-Wildfire", "obj_desc": "Land fire: Brush, bush, Pasture", "det_method": "Photo-interpretation", "notation": "Active Flames", "dmg_src_id": 2 }, "geometry": { "type": "Point", "coordinates": [ 116.115219664000051, -31.721669082999938 ] } },
{ "type": "Feature", "properties": { "event_type": "8-Wildfire", "obj_desc": "Land fire: Brush, bush, Pasture", "det_method": "Photo-interpretation", "notation": "Active Flames", "dmg_src_id": 2 }, "geometry": { "type": "Point", "coordinates": [ 116.113390678000087, -31.723118413999941 ] } },
{ "type": "Feature", "properties": { "event_type": "8-Wildfire", "obj_desc": "Land fire: Brush, bush, Pasture", "det_method": "Photo-interpretation", "notation": "Active Flames", "dmg_src_id": 2 }, "geometry": { "type": "Point", "coordinates": [ 116.099212134000027, -31.703367424999954 ] } },
{ "type": "Feature", "properties": { "event_type": "8-Wildfire", "obj_desc": "Land fire: Brush, bush, Pasture", "det_method": "Photo-interpretation", "notation": "Active Flames", "dmg_src_id": 2 }, "geometry": { "type": "Point", "coordinates": [ 116.266262811000047, -31.755517729999951 ] } },
{ "type": "Feature", "properties": { "event_type": "8-Wildfire", "obj_desc": "Land fire: Brush, bush, Pasture", "det_method": "Photo-interpretation", "notation": "Active Flames", "dmg_src_id": 2 }, "geometry": { "type": "Point", "coordinates": [ 116.119050219000087, -31.711430456999949 ] } },
{ "type": "Feature", "properties": { "event_type": "8-Wildfire", "obj_desc": "Land fire: Brush, bush, Pasture", "det_method": "Photo-interpretation", "notation": "Active Flames", "dmg_src_id": 2 }, "geometry": { "type": "Point", "coordinates": [ 116.101480516000038, -31.705555603999983 ] } },
{ "type": "Feature", "properties": { "event_type": "8-Wildfire", "obj_desc": "Land fire: Brush, bush, Pasture", "det_method": "Photo-interpretation", "notation": "Active Flames", "dmg_src_id": 2 }, "geometry": { "type": "Point", "coordinates": [ 116.101780412000039, -31.703409411999928 ] } },
{ "type": "Feature", "properties": { "event_type": "8-Wildfire", "obj_desc": "Land fire: Brush, bush, Pasture", "det_method": "Photo-interpretation", "notation": "Active Flames", "dmg_src_id": 2 }, "geometry": { "type": "Point", "coordinates": [ 116.135421695000105, -31.724790861999963 ] } },
{ "type": "Feature", "properties": { "event_type": "8-Wildfire", "obj_desc": "Land fire: Brush, bush, Pasture", "det_method": "Photo-interpretation", "notation": "Active Flames", "dmg_src_id": 2 }, "geometry": { "type": "Point", "coordinates": [ 116.250222008000037, -31.766599121999946 ] } }
]
}
